{
  "events": [
    {
      "eventName": "Music Festival",
      "startDate": "2023-01-20",
      "endDate": "2023-01-21",
      "id": 1
    },
    {
      "eventName": "Food Festival",
      "startDate": "2023-02-01",
      "endDate": "2023-02-02",
      "id": 2
    },
    {
      "eventName": "Event name",
      "startDate": "",
      "endDate": "",
      "id": 3
    },
    {
      "eventName": "dgff",
      "startDate": "",
      "endDate": "",
      "id": 4
    },
    {
      "eventName": "dgff",
      "startDate": "",
      "endDate": "",
      "id": 5
    },
    {
      "eventName": "dgff",
      "startDate": "",
      "endDate": "",
      "id": 6
    },
    {
      "eventName": "dgff",
      "startDate": "",
      "endDate": "",
      "id": 7
    },
    {
      "eventName": "dgff",
      "startDate": "",
      "endDate": "",
      "id": 8
    },
    {
      "eventName": "dgff",
      "startDate": "",
      "endDate": "",
      "id": 9
    },
    {
      "eventName": "dgff",
      "startDate": "",
      "endDate": "",
      "id": 10
    },
    {
      "eventName": "dgff",
      "startDate": "",
      "endDate": "",
      "id": 11
    },
    {
      "eventName": "dgff",
      "startDate": "",
      "endDate": "",
      "id": 12
    },
    {
      "eventName": "dgff",
      "startDate": "",
      "endDate": "",
      "id": 13
    },
    {
      "eventName": "dgff",
      "startDate": "",
      "endDate": "",
      "id": 14
    },
    {
      "eventName": "dgff",
      "startDate": "",
      "endDate": "",
      "id": 15
    },
    {
      "eventName": "dgff",
      "startDate": "",
      "endDate": "",
      "id": 16
    },
    {
      "eventName": "dgff",
      "startDate": "",
      "endDate": "",
      "id": 17
    },
    {
      "eventName": "dgff",
      "startDate": "",
      "endDate": "",
      "id": 18
    },
    {
      "eventName": "dgff",
      "startDate": "",
      "endDate": "",
      "id": 19
    },
    {
      "eventName": "dgff",
      "startDate": "",
      "endDate": "",
      "id": 20
    },
    {
      "eventName": "dgff",
      "startDate": "",
      "endDate": "",
      "id": 21
    },
    {
      "eventName": "dgff",
      "startDate": "",
      "endDate": "",
      "id": 22
    },
    {
      "eventName": "dgff",
      "startDate": "",
      "endDate": "",
      "id": 23
    },
    {
      "eventName": "dgff",
      "startDate": "",
      "endDate": "",
      "id": 24
    },
    {
      "eventName": "dgff",
      "startDate": "",
      "endDate": "",
      "id": 25
    },
    {
      "eventName": "dgff",
      "startDate": "",
      "endDate": "",
      "id": 26
    },
    {
      "eventName": "dgff",
      "startDate": "2023-01-10",
      "endDate": "2023-01-31",
      "id": 27
    },
    {
      "eventName": "dgff",
      "startDate": "2023-01-10",
      "endDate": "2023-01-31",
      "id": 28
    },
    {
      "eventName": "dgff",
      "startDate": "2023-01-10",
      "endDate": "2023-01-31",
      "id": 29
    },
    {
      "eventName": "dgff",
      "startDate": "2023-01-10",
      "endDate": "2023-01-31",
      "id": 30
    },
    {
      "eventName": "dgff",
      "startDate": "2023-01-10",
      "endDate": "2023-01-31",
      "id": 31
    },
    {
      "eventName": "dgff",
      "startDate": "2023-01-10",
      "endDate": "2023-01-31",
      "id": 32
    },
    {
      "eventName": "dgff",
      "startDate": "2023-01-10",
      "endDate": "2023-01-31",
      "id": 33
    },
    {
      "eventName": "dgff",
      "startDate": "2023-01-10",
      "endDate": "2023-01-31",
      "id": 34
    }
  ]
}